MinuteMail/MinuteMail.py
MinuteMail/__init__.py
MinuteMail-0.2.0.dist-info/METADATA
MinuteMail-0.2.0.dist-info/WHEEL
MinuteMail-0.2.0.dist-info/top_level.txt
MinuteMail-0.2.0.dist-info/RECORD
