Metadata-Version: 2.1
Name: MinuteMail
Version: 0.2.0
Summary: Package that lets you generate email addresses and read their mail through dropmail.me websocket.
Home-page: https://github.com/memst/MinuteMail
Author: memst
Author-email: stankev.martynas@gmail.com
License: UNKNOWN
Platform: UNKNOWN
Classifier: Programming Language :: Python :: 3
Classifier: Operating System :: OS Independent
Requires-Python: >=3.6
Requires-Dist: websocket-client
